services/__init__.py
services/admin.py
services/models.py
services/tests.py
services/views.py
services/migrations/0001_initial.py
services/migrations/0002_service_verify.py
services/migrations/__init__.py
django_easy_services-0.2.dist-info/AUTHORS
django_easy_services-0.2.dist-info/LICENSE
django_easy_services-0.2.dist-info/METADATA
django_easy_services-0.2.dist-info/WHEEL
django_easy_services-0.2.dist-info/top_level.txt
django_easy_services-0.2.dist-info/RECORD
