Metadata-Version: 2.1
Name: django-easy-services
Version: 0.2
Summary: A simple Django app to handle services request.
Home-page: https://github.com/lmendes86/django-services/
Author: Lucas Mendes
Author-email: lucasam86@gmail.com
Maintainer: Lucas Mendes
Maintainer-email: lucasam86@gmail.com
License: MIT License
Platform: UNKNOWN
Classifier: Environment :: Web Environment
Classifier: Framework :: Django
Classifier: Intended Audience :: Developers
Classifier: License :: OSI Approved :: MIT License
Classifier: Operating System :: OS Independent
Classifier: Programming Language :: Python
Classifier: Programming Language :: Python :: 3
Classifier: Topic :: Internet :: WWW/HTTP
Classifier: Topic :: Internet :: WWW/HTTP :: Dynamic Content
Requires-Dist: Django (>=1.8)
Requires-Dist: requests (>=2.20.0)
Requires-Dist: asyncio (>=3.4.3)
